[{"model": "products.product_category", "pk": 1, "fields": {"category": 1, "product": 1}}, {"model": "products.product_category", "pk": 2, "fields": {"category": 1, "product": 2}}, {"model": "products.product_category", "pk": 3, "fields": {"category": 1, "product": 3}}, {"model": "products.product_category", "pk": 4, "fields": {"category": 1, "product": 4}}, {"model": "products.product_category", "pk": 5, "fields": {"category": 1, "product": 5}}, {"model": "products.product_category", "pk": 6, "fields": {"category": 1, "product": 6}}, {"model": "products.product_category", "pk": 7, "fields": {"category": 1, "product": 7}}, {"model": "products.product_category", "pk": 8, "fields": {"category": 2, "product": 8}}, {"model": "products.product_category", "pk": 9, "fields": {"category": 2, "product": 9}}, {"model": "products.product_category", "pk": 10, "fields": {"category": 4, "product": 10}}, {"model": "products.product_category", "pk": 11, "fields": {"category": 4, "product": 11}}, {"model": "products.product_category", "pk": 12, "fields": {"category": 4, "product": 12}}, {"model": "products.product_category", "pk": 13, "fields": {"category": 4, "product": 13}}, {"model": "products.product_category", "pk": 14, "fields": {"category": 4, "product": 14}}, {"model": "products.product_category", "pk": 15, "fields": {"category": 4, "product": 15}}, {"model": "products.product_category", "pk": 16, "fields": {"category": 4, "product": 16}}, {"model": "products.product_category", "pk": 17, "fields": {"category": 3, "product": 17}}, {"model": "products.product_category", "pk": 18, "fields": {"category": 3, "product": 18}}]